combustion_ble/__init__.py
combustion_ble/ble_manager.py
combustion_ble/connection_manager.py
combustion_ble/const.py
combustion_ble/device_manager.py
combustion_ble/dfu_manager.py
combustion_ble/exceptions.py
combustion_ble/instant_read_filter.py
combustion_ble/logged_probe_data_count.py
combustion_ble/logger.py
combustion_ble/message_handlers.py
combustion_ble/probe_temperature_log.py
combustion_ble/py.typed
combustion_ble/version.py
combustion_ble/ble_data/__init__.py
combustion_ble/ble_data/advertising_data.py
combustion_ble/ble_data/battery_status_virtual_sensors.py
combustion_ble/ble_data/food_safe_data.py
combustion_ble/ble_data/food_safe_state.py
combustion_ble/ble_data/hop_count.py
combustion_ble/ble_data/mode_id.py
combustion_ble/ble_data/prediction_log.py
combustion_ble/ble_data/prediction_mode.py
combustion_ble/ble_data/prediction_state.py
combustion_ble/ble_data/prediction_status.py
combustion_ble/ble_data/prediction_type.py
combustion_ble/ble_data/probe_status.py
combustion_ble/ble_data/probe_temperatures.py
combustion_ble/ble_data/virtual_sensors.py
combustion_ble/devices/__init__.py
combustion_ble/devices/device.py
combustion_ble/devices/meat_net_node.py
combustion_ble/devices/probe.py
combustion_ble/prediction/prediction_info.py
combustion_ble/prediction/prediction_manager.py
combustion_ble/uart/__init__.py
combustion_ble/uart/log_request.py
combustion_ble/uart/log_response.py
combustion_ble/uart/message_type.py
combustion_ble/uart/read_over_temperature.py
combustion_ble/uart/request.py
combustion_ble/uart/response.py
combustion_ble/uart/response_from_data.py
combustion_ble/uart/session_info.py
combustion_ble/uart/set_color.py
combustion_ble/uart/set_id.py
combustion_ble/uart/set_prediction.py
combustion_ble/uart/meatnet/__init__.py
combustion_ble/uart/meatnet/node_heartbeat_request.py
combustion_ble/uart/meatnet/node_message_type.py
combustion_ble/uart/meatnet/node_probe_status_request.py
combustion_ble-0.3.3.dist-info/LICENSE
combustion_ble-0.3.3.dist-info/METADATA
combustion_ble-0.3.3.dist-info/WHEEL
combustion_ble-0.3.3.dist-info/top_level.txt
combustion_ble-0.3.3.dist-info/RECORD
