Metadata-Version: 2.1
Name: combustion_ble
Version: 0.3.3
Summary: SDK for communicating with Combustion Bluetooth devices
Author-email: Larry Gregory <lgregorydev@gmail.com>
License: Apache License
Project-URL: Homepage, https://github.com/legrego/combustion_ble
Project-URL: Repository, https://github.com/legrego/combustion_ble
Project-URL: Changelog, https://github.com/legrego/combustion_ble/blob/main/CHANGELOG.md
Project-URL: Documentation, https://combustion_ble.readthedocs.io/
Classifier: Development Status :: 3 - Alpha
Classifier: Programming Language :: Python :: 3
Classifier: License :: OSI Approved :: Apache Software License
Classifier: Operating System :: OS Independent
Requires-Python: >=3.11
License-File: LICENSE
Requires-Dist: bitstring
Requires-Dist: bleak
Provides-Extra: dev
Requires-Dist: ruff ; extra == 'dev'
Requires-Dist: mypy <1.9,>=1.0 ; extra == 'dev'
Requires-Dist: black <25.0,>=23.0 ; extra == 'dev'
Requires-Dist: isort <5.14,>=5.12 ; extra == 'dev'
Requires-Dist: pytest ; extra == 'dev'
Requires-Dist: pytest-sphinx ; extra == 'dev'
Requires-Dist: pytest-cov ; extra == 'dev'
Requires-Dist: twine >=1.11.0 ; extra == 'dev'
Requires-Dist: build ; extra == 'dev'
Requires-Dist: setuptools ; extra == 'dev'
Requires-Dist: wheel ; extra == 'dev'
Requires-Dist: Sphinx <7.3.0,>=4.3.0 ; extra == 'dev'
Requires-Dist: furo ==2024.1.29 ; extra == 'dev'
Requires-Dist: myst-parser <2.1,>=1.0 ; extra == 'dev'
Requires-Dist: sphinx-copybutton ==0.5.2 ; extra == 'dev'
Requires-Dist: sphinx-autobuild ==2024.2.4 ; extra == 'dev'
Requires-Dist: sphinx-autodoc-typehints ==2.0.0 ; extra == 'dev'
Requires-Dist: packaging ; extra == 'dev'
Requires-Dist: live ; extra == 'dev'
